LICENSE
README.md
setup.py
bmobpy/__init__.py
bmobpy/bmob.py
bmobpy/test.py
bmobpy.egg-info/PKG-INFO
bmobpy.egg-info/SOURCES.txt
bmobpy.egg-info/dependency_links.txt
bmobpy.egg-info/requires.txt
bmobpy.egg-info/top_level.txt