Metadata-Version: 2.1
Name: bmobpy
Version: 1.10.0
Summary: Bmob后端云的Python SDK
Home-page: https://www.bmobapp.com
Author: www.bmobapp.com
Author-email: admin@bmobapp.com
License: MIT
Keywords: Bmob后端云 Python SDK
License-File: LICENSE
Requires-Dist: websockets
